src/__init__.py
src/__main__.py
src/config.py
src/file_helpers.py
src/optimize.py
src/service_actions.py
src/trie.py
iam_minify-0.0.4.dist-info/LICENSE
iam_minify-0.0.4.dist-info/METADATA
iam_minify-0.0.4.dist-info/WHEEL
iam_minify-0.0.4.dist-info/entry_points.txt
iam_minify-0.0.4.dist-info/top_level.txt
iam_minify-0.0.4.dist-info/RECORD
