Metadata-Version: 2.1
Name: iam-minify
Version: 0.0.4
Summary: Minify IAM actions using wildcards to save up as many characters as possible without granting unintended permissions
Home-page: https://github.com/imduchy/iam-minify
Author: imduchy
Author-email: jakub@duchy.sk
License: MIT
Keywords: AWS IAM policy minify
License-File: LICENSE
Requires-Dist: requests
